{
  "db_name": "PostgreSQL",
  "query": "SELECT id, workspace_id, name, color, end_date, updated_at, deleted_at FROM project\n           WHERE workspace_id = ANY($1) AND ($2::timestamptz IS NULL OR updated_at > $2)",
  "describe": {
    "columns": [
      {
        "ordinal": 0,
        "name": "id",
        "type_info": "Uuid"
      },
      {
        "ordinal": 1,
        "name": "workspace_id",
        "type_info": "Uuid"
      },
      {
        "ordinal": 2,
        "name": "name",
        "type_info": "Text"
      },
      {
        "ordinal": 3,
        "name": "color",
        "type_info": "Text"
      },
      {
        "ordinal": 4,
        "name": "end_date",
        "type_info": "Date"
      },
      {
        "ordinal": 5,
        "name": "updated_at",
        "type_info": "Timestamptz"
      },
      {
        "ordinal": 6,
        "name": "deleted_at",
        "type_info": "Timestamptz"
      }
    ],
    "parameters": {
      "Left": [
        "UuidArray",
        "Timestamptz"
      ]
    },
    "nullable": [
      false,
      false,
      false,
      false,
      true,
      false,
      true
    ]
  },
  "hash": "2c007ae48776589426d5204ffeb9b211b4e0e40d3d2624a7e1661403719c4e53"
}
